json_repair/__init__.py
json_repair/__main__.py
json_repair/json_parser.py
json_repair/json_repair.py
json_repair/parse_array.py
json_repair/parse_comment.py
json_repair/parse_number.py
json_repair/parse_object.py
json_repair/parse_string.py
json_repair/py.typed
json_repair/parse_string_helpers/parse_boolean_or_null.py
json_repair/parse_string_helpers/parse_json_llm_block.py
json_repair/utils/constants.py
json_repair/utils/json_context.py
json_repair/utils/object_comparer.py
json_repair/utils/string_file_wrapper.py
json_repair-0.54.dist-info/licenses/LICENSE
json_repair-0.54.dist-info/METADATA
json_repair-0.54.dist-info/WHEEL
json_repair-0.54.dist-info/entry_points.txt
json_repair-0.54.dist-info/top_level.txt
json_repair-0.54.dist-info/RECORD
