Metadata-Version: 2.4
Name: json_repair
Version: 0.54
Summary: A package to repair broken json strings
Author-email: Stefano Baccianella <4247706+mangiucugna@users.noreply.github.com>
License-Expression: MIT
Project-URL: Homepage, https://github.com/mangiucugna/json_repair/
Project-URL: Bug Tracker, https://github.com/mangiucugna/json_repair/issues
Project-URL: Live demo, https://mangiucugna.github.io/json_repair/
Keywords: JSON,REPAIR,LLM,PARSER
Classifier: Programming Language :: Python :: 3
Classifier: Operating System :: OS Independent
Requires-Python: >=3.10
License-File: LICENSE
Dynamic: license-file
